{
	"entries": [
		{
				"message": "Running BurgerShot.script",
				"identifier": "START",
				"timestamp": "2019-06-23 21:02:56.700 -0500"
			},
		{
				"message": "(Duration:\"0.705\", Errors:\"1\", Exceptions:\"0\", StartTime:\"2019-06-23 21:02:56 -0500\", Successes:\"0\", TestCase:\"BurgerShot.script\", Warnings:\"0\")",
				"identifier": "EndTestCase",
				"timestamp": "2019-06-23 21:02:57.411 -0500"
			},
		{
				"image": "Screen_Error.png",
				"message": "SRUN_InvalidValueExpr Unable to take value of expression ' {⏎\\t\"DEFAULT\":{⏎\\t\\t\"applicaiton\":\"C:\\Users\\rc050176\\eclipse\\java-2019-06\\eclipse\\eclipse.exe\",⏎...' (reason: (null)) -- Execution Time 0:00:01 BurgerShot.script",
				"identifier": "FAILURE",
				"timestamp": "2019-06-23 21:02:57.625 -0500"
			}
	],
	"createdTimestamp": "2019-06-24 02:02:56.703 +0000"
}